odoo/addons/account_move_original_partner/README.rst
odoo/addons/account_move_original_partner/__init__.py
odoo/addons/account_move_original_partner/__manifest__.py
odoo/addons/account_move_original_partner/hooks.py
odoo/addons/account_move_original_partner/i18n/account_move_original_partner.pot
odoo/addons/account_move_original_partner/i18n/ca.po
odoo/addons/account_move_original_partner/i18n/es.po
odoo/addons/account_move_original_partner/i18n/it.po
odoo/addons/account_move_original_partner/models/__init__.py
odoo/addons/account_move_original_partner/models/account_move.py
odoo/addons/account_move_original_partner/readme/CONTRIBUTORS.rst
odoo/addons/account_move_original_partner/readme/CREDITS.rst
odoo/addons/account_move_original_partner/readme/DESCRIPTION.rst
odoo/addons/account_move_original_partner/static/description/icon.png
odoo/addons/account_move_original_partner/static/description/index.html
odoo/addons/account_move_original_partner/views/account_move.xml
odoo14_addon_account_move_original_partner-14.0.1.0.1.dev10.dist-info/METADATA
odoo14_addon_account_move_original_partner-14.0.1.0.1.dev10.dist-info/WHEEL
odoo14_addon_account_move_original_partner-14.0.1.0.1.dev10.dist-info/top_level.txt
odoo14_addon_account_move_original_partner-14.0.1.0.1.dev10.dist-info/RECORD
